{
    "adult": false,
    "backdrop_path": "/y8G11KP4qNY2251ufNezKF92EAR.jpg",
    "belongs_to_collection": null,
    "budget": 0,
    "genres": [
        {
            "id": 27,
            "name": "Horror"
        },
        {
            "id": 14,
            "name": "Fantasy"
        },
        {
            "id": 18,
            "name": "Drama"
        }
    ],
    "homepage": "",
    "id": 30959,
    "imdb_id": "tt0058279",
    "original_language": "ja",
    "original_title": "\u602a\u8ac7",
    "overview": "Taking its title from an archaic Japanese word meaning \"ghost story,\" this anthology adapts four folk tales. A penniless samurai marries for money with tragic results. A man stranded in a blizzard is saved by Yuki the Snow Maiden, but his rescue comes at a cost. Blind musician Hoichi is forced to perform for an audience of ghosts. An author relates the story of a samurai who sees another warrior's reflection in his teacup.",
    "popularity": 21.137,
    "poster_path": "/cfcIjq4V8GxtMN6GU3WnufTM9cD.jpg",
    "production_companies": [
        {
            "id": 14879,
            "logo_path": null,
            "name": "Bungei",
            "origin_country": ""
        },
        {
            "id": 882,
            "logo_path": "/iDw9Xxok1d9WAM2zFicI8p3khTH.png",
            "name": "TOHO",
            "origin_country": "JP"
        },
        {
            "id": 7040,
            "logo_path": null,
            "name": "Ninjin Club",
            "origin_country": "JP"
        },
        {
            "id": 14881,
            "logo_path": null,
            "name": "Toyo Kogyo Kabushiki Kaisha",
            "origin_country": ""
        }
    ],
    "production_countries": [
        {
            "iso_3166_1": "JP",
            "name": "Japan"
        }
    ],
    "release_date": "1965-01-06",
    "revenue": 0,
    "runtime": 183,
    "spoken_languages": [
        {
            "english_name": "Japanese",
            "iso_639_1": "ja",
            "name": "\u65e5\u672c\u8a9e"
        }
    ],
    "status": "Released",
    "tagline": "In the tradition of \"RASHOMON\" and \"GATE OF HELL\".",
    "title": "Kwaidan",
    "video": false,
    "vote_average": 7.696,
    "vote_count": 335,
    "credits": {
        "cast": [
            {
                "adult": false,
                "gender": 1,
                "id": 85307,
                "known_for_department": "Acting",
                "name": "Michiyo Aratama",
                "original_name": "Michiyo Aratama",
                "popularity": 3.767,
                "profile_path": "/1iaZBOpb6NAr9naDph4y4kUhPWU.jpg",
                "cast_id": 9,
                "character": "First Wife (segment \"The Black Hair\")",
                "credit_id": "52fe444f9251416c9100c321",
                "order": 0
            },
            {
                "adult": false,
                "gender": 1,
                "id": 111235,
                "known_for_department": "Acting",
                "name": "Misako Watanabe",
                "original_name": "Misako Watanabe",
                "popularity": 2.132,
                "profile_path": "/3jLsF5Qs5FYyweHxhEqkWwR6aiQ.jpg",
                "cast_id": 10,
                "character": "Second Wife (segment \"The Black Hair\")",
                "credit_id": "52fe444f9251416c9100c325",
                "order": 1
            },
            {
                "adult": false,
                "gender": 2,
                "id": 76975,
                "known_for_department": "Acting",
                "name": "Rentaro Mikuni",
                "original_name": "Rentaro Mikuni",
                "popularity": 5.995,
                "profile_path": "/o4zQO6RDWTH9v7hQNuRsfYgsJKq.jpg",
                "cast_id": 11,
                "character": "Husband (segment \"The Black Hair\")",
                "credit_id": "52fe444f9251416c9100c329",
                "order": 2
            },
            {
                "adult": false,
                "gender": 2,
                "id": 72539,
                "known_for_department": "Acting",
                "name": "Kenjir\u014d Ishiyama",
                "original_name": "Kenjir\u014d Ishiyama",
                "popularity": 3.263,
                "profile_path": "/6Qc64jqkcRY1rQ7e8yRwhIFF0nB.jpg",
                "cast_id": 12,
                "character": "Father (segment \"The Black Hair\")",
                "credit_id": "52fe444f9251416c9100c32d",
                "order": 3
            },
            {
                "adult": false,
                "gender": 0,
                "id": 142492,
                "known_for_department": "Acting",
                "name": "Ranko Akagi",
                "original_name": "Ranko Akagi",
                "popularity": 1.723,
                "profile_path": null,
                "cast_id": 13,
                "character": "Mother (segment \"The Black Hair\")",
                "credit_id": "52fe444f9251416c9100c331",
                "order": 4
            },
            {
                "adult": false,
                "gender": 1,
                "id": 552640,
                "known_for_department": "Acting",
                "name": "Fumie Kitahara",
                "original_name": "Fumie Kitahara",
                "popularity": 1.426,
                "profile_path": "/dE9HcKFIIJhO5c01GosNW8iA02r.jpg",
                "cast_id": 14,
                "character": "(segment \"The Black Hair\")",
                "credit_id": "52fe444f9251416c9100c335",
                "order": 5
            },
            {
                "adult": false,
                "gender": 2,
                "id": 552641,
                "known_for_department": "Acting",
                "name": "Kappei Matsumoto",
                "original_name": "Kappei Matsumoto",
                "popularity": 3.361,
                "profile_path": null,
                "cast_id": 15,
                "character": "(segment \"The Black Hair\") (uncredited)",
                "credit_id": "52fe444f9251416c9100c339",
                "order": 6
            },
            {
                "adult": false,
                "gender": 1,
                "id": 552642,
                "known_for_department": "Acting",
                "name": "Yoshiko Ieda",
                "original_name": "Yoshiko Ieda",
                "popularity": 1.287,
                "profile_path": null,
                "cast_id": 16,
                "character": "(segment \"The Black Hair\") (uncredited)",
                "credit_id": "52fe444f9251416c9100c33d",
                "order": 7
            },
            {
                "adult": false,
                "gender": 1,
                "id": 552643,
                "known_for_department": "Acting",
                "name": "Otome Tsukimiya",
                "original_name": "Otome Tsukimiya",
                "popularity": 1.4,
                "profile_path": "/xaaLNOk1rgtcIsabwacVXNF8fI8.jpg",
                "cast_id": 17,
                "character": "(segment \"The Black Hair\") (uncredited)",
                "credit_id": "52fe444f9251416c9100c341",
                "order": 8
            },
            {
                "adult": false,
                "gender": 0,
                "id": 552644,
                "known_for_department": "Acting",
                "name": "Kenz\u014d Tanaka",
                "original_name": "Kenz\u014d Tanaka",
                "popularity": 0.694,
                "profile_path": null,
                "cast_id": 18,
                "character": "(segment \"The Black Hair\") (uncredited)",
                "credit_id": "52fe444f9251416c9100c345",
                "order": 9
            },
            {
                "adult": false,
                "gender": 0,
                "id": 552645,
                "known_for_department": "Acting",
                "name": "Kiyoshi Nakano",
                "original_name": "Kiyoshi Nakano",
                "popularity": 0.6,
                "profile_path": null,
                "cast_id": 19,
                "character": "(segment \"The Black Hair\") (uncredited)",
                "credit_id": "52fe444f9251416c9100c349",
                "order": 10
            },
            {
                "adult": false,
                "gender": 2,
                "id": 70131,
                "known_for_department": "Acting",
                "name": "Tatsuya Nakadai",
                "original_name": "Tatsuya Nakadai",
                "popularity": 9.551,
                "profile_path": "/4LygOe0vFQplLIft5IUWI5OewPX.jpg",
                "cast_id": 20,
                "character": "Minokichi (segment \"The Woman of the Snow\")",
                "credit_id": "52fe444f9251416c9100c34d",
                "order": 11
            },
            {
                "adult": false,
                "gender": 1,
                "id": 122828,
                "known_for_department": "Acting",
                "name": "Keiko Kishi",
                "original_name": "Keiko Kishi",
                "popularity": 6.763,
                "profile_path": "/1JM32v7ZQyPeYJeyUTQaSvCXK8P.jpg",
                "cast_id": 21,
                "character": "Yuki the Snow Maiden (segment \"The Woman of the Snow\")",
                "credit_id": "52fe444f9251416c9100c351",
                "order": 12
            },
            {
                "adult": false,
                "gender": 1,
                "id": 213497,
                "known_for_department": "Acting",
                "name": "Y\u016bko Mochizuki",
                "original_name": "Y\u016bko Mochizuki",
                "popularity": 3.369,
                "profile_path": "/5TUdCo50ZN3aX8mYw152hBb9rqL.jpg",
                "cast_id": 22,
                "character": "Minokichi's Mother (segment \"The Woman of the Snow\")",
                "credit_id": "52fe444f9251416c9100c355",
                "order": 13
            },
            {
                "adult": false,
                "gender": 1,
                "id": 110300,
                "known_for_department": "Acting",
                "name": "Kin Sugai",
                "original_name": "Kin Sugai",
                "popularity": 1.878,
                "profile_path": "/w0OXsibm2sLfe9CVg9L6IJ8A7ep.jpg",
                "cast_id": 23,
                "character": "Village Woman (segment \"The Woman of the Snow\")",
                "credit_id": "52fe444f9251416c9100c359",
                "order": 14
            },
            {
                "adult": false,
                "gender": 1,
                "id": 106161,
                "known_for_department": "Acting",
                "name": "Noriko Sengoku",
                "original_name": "Noriko Sengoku",
                "popularity": 2.76,
                "profile_path": "/1LXOl1fSe0H04AyEJjPeBEJbWdo.jpg",
                "cast_id": 24,
                "character": "Village Woman (segment \"The Woman of the Snow\")",
                "credit_id": "52fe444f9251416c9100c35d",
                "order": 15
            },
            {
                "adult": false,
                "gender": 1,
                "id": 552646,
                "known_for_department": "Acting",
                "name": "Akiko Nomura",
                "original_name": "Akiko Nomura",
                "popularity": 2.75,
                "profile_path": null,
                "cast_id": 25,
                "character": "(segment \"The Woman of the Snow\") (uncredited)",
                "credit_id": "52fe444f9251416c9100c361",
                "order": 16
            },
            {
                "adult": false,
                "gender": 2,
                "id": 552343,
                "known_for_department": "Acting",
                "name": "Torahiko Hamada",
                "original_name": "Torahiko Hamada",
                "popularity": 3.044,
                "profile_path": "/7blVOCQXrhzVydmfHt9QmLgbRoM.jpg",
                "cast_id": 26,
                "character": "(segment \"The Woman of the Snow\") (uncredited)",
                "credit_id": "52fe444f9251416c9100c365",
                "order": 17
            },
            {
                "adult": false,
                "gender": 2,
                "id": 97629,
                "known_for_department": "Acting",
                "name": "Jun Hamamura",
                "original_name": "Jun Hamamura",
                "popularity": 2.038,
                "profile_path": "/9kGy2anW69XcL773DxjDHoEOq03.jpg",
                "cast_id": 27,
                "character": "(segment \"The Woman of the Snow\")",
                "credit_id": "52fe444f9251416c9100c369",
                "order": 18
            },
            {
                "adult": false,
                "gender": 2,
                "id": 70121,
                "known_for_department": "Acting",
                "name": "Katsuo Nakamura",
                "original_name": "Katsuo Nakamura",
                "popularity": 1.966,
                "profile_path": "/wWRFSaZQTl1XeEdkbwW4HP23VS6.jpg",
                "cast_id": 28,
                "character": "Hoichi (segment \"Hoichi the Earless\")",
                "credit_id": "52fe444f9251416c9100c36d",
                "order": 19
            },
            {
                "adult": false,
                "gender": 2,
                "id": 10071,
                "known_for_department": "Acting",
                "name": "Tetsur\u014d Tamba",
                "original_name": "Tetsur\u014d Tamba",
                "popularity": 5.241,
                "profile_path": "/ihugQ2afio03fcKSGXdkcQKTVmt.jpg",
                "cast_id": 29,
                "character": "Warrior (segment \"Hoichi the Earless\")",
                "credit_id": "52fe444f9251416c9100c371",
                "order": 20
            },
            {
                "adult": false,
                "gender": 2,
                "id": 7453,
                "known_for_department": "Acting",
                "name": "Takashi Shimura",
                "original_name": "Takashi Shimura",
                "popularity": 5.901,
                "profile_path": "/ydyAm2vyBbEPZRICIMqqjDm0NM9.jpg",
                "cast_id": 30,
                "character": "Head Priest (segment \"Hoichi the Earless\")",
                "credit_id": "52fe444f9251416c9100c375",
                "order": 21
            },
            {
                "adult": false,
                "gender": 2,
                "id": 222963,
                "known_for_department": "Acting",
                "name": "Yoichi Hayashi",
                "original_name": "Yoichi Hayashi",
                "popularity": 2.548,
                "profile_path": "/4KnfotppCUekdwASI6GP0xzF8Fr.jpg",
                "cast_id": 31,
                "character": "Attendant (segment \"Hoichi the Earless\")",
                "credit_id": "52fe444f9251416c9100c379",
                "order": 22
            },
            {
                "adult": false,
                "gender": 1,
                "id": 552647,
                "known_for_department": "Acting",
                "name": "Eiko Muramatsu",
                "original_name": "Eiko Muramatsu",
                "popularity": 1.803,
                "profile_path": "/tzb4BY5qUJ0hvmd6rVlZHJwAUq5.jpg",
                "cast_id": 32,
                "character": "Kenreiinmon (segment \"Hoichi the Earless\")",
                "credit_id": "52fe444f9251416c9100c37d",
                "order": 23
            },
            {
                "adult": false,
                "gender": 2,
                "id": 99247,
                "known_for_department": "Acting",
                "name": "Kunie Tanaka",
                "original_name": "Kunie Tanaka",
                "popularity": 9.96,
                "profile_path": "/i5CPYwU2cmCRYFnTrsOHFyqslcO.jpg",
                "cast_id": 33,
                "character": "Yasaku (segment \"Hoichi the Earless\")",
                "credit_id": "52fe444f9251416c9100c381",
                "order": 24
            },
            {
                "adult": false,
                "gender": 2,
                "id": 63707,
                "known_for_department": "Acting",
                "name": "Kazuo Kitamura",
                "original_name": "Kazuo Kitamura",
                "popularity": 1.269,
                "profile_path": "/qjkqx9yEL5ZMavws73Uu4u4OsY2.jpg",
                "cast_id": 34,
                "character": "Tomomori (segment \"Hoichi the Earless\")",
                "credit_id": "52fe444f9251416c9100c385",
                "order": 25
            },
            {
                "adult": false,
                "gender": 2,
                "id": 118993,
                "known_for_department": "Acting",
                "name": "Ichir\u014d Nakatani",
                "original_name": "Ichir\u014d Nakatani",
                "popularity": 2.793,
                "profile_path": "/yGWAZguLnWvXW9xcAIE7Eo6VGfU.jpg",
                "cast_id": 35,
                "character": "(segment \"Hoichi the Earless\") (uncredited)",
                "credit_id": "52fe444f9251416c9100c389",
                "order": 26
            },
            {
                "adult": false,
                "gender": 0,
                "id": 552648,
                "known_for_department": "Acting",
                "name": "Masanori Tomotake",
                "original_name": "Masanori Tomotake",
                "popularity": 0.6,
                "profile_path": null,
                "cast_id": 36,
                "character": "(segment \"Hoichi the Earless\") (uncredited)",
                "credit_id": "52fe444f9251416c9100c38d",
                "order": 27
            },
            {
                "adult": false,
                "gender": 2,
                "id": 552649,
                "known_for_department": "Acting",
                "name": "Tokue Hanazawa",
                "original_name": "Tokue Hanazawa",
                "popularity": 4.352,
                "profile_path": "/1uHrAp1aieQw2hgmkhaBDSgxMLD.jpg",
                "cast_id": 37,
                "character": "(segment \"Hoichi the Earless\") (uncredited)",
                "credit_id": "52fe444f9251416c9100c391",
                "order": 28
            },
            {
                "adult": false,
                "gender": 1,
                "id": 552650,
                "known_for_department": "Acting",
                "name": "Shizue Natsukawa",
                "original_name": "Shizue Natsukawa",
                "popularity": 1.469,
                "profile_path": "/nqmqyK3E288XKcsVAllsjG4gMwW.jpg",
                "cast_id": 38,
                "character": "Tokiko (segment \"Hoichi the Earless\") (uncredited)",
                "credit_id": "52fe444f9251416c9100c395",
                "order": 29
            },
            {
                "adult": false,
                "gender": 2,
                "id": 552651,
                "known_for_department": "Acting",
                "name": "Shin Tatsuoka",
                "original_name": "Shin Tatsuoka",
                "popularity": 0.98,
                "profile_path": null,
                "cast_id": 39,
                "character": "(segment \"Hoichi the Earless\") (uncredited)",
                "credit_id": "52fe444f9251416c9100c399",
                "order": 30
            },
            {
                "adult": false,
                "gender": 1,
                "id": 552652,
                "known_for_department": "Acting",
                "name": "Makiko Kitashiro",
                "original_name": "Makiko Kitashiro",
                "popularity": 1.38,
                "profile_path": null,
                "cast_id": 40,
                "character": "(segment \"Hoichi the Earless\") (uncredited)",
                "credit_id": "52fe444f9251416c9100c39d",
                "order": 31
            },
            {
                "adult": false,
                "gender": 2,
                "id": 142489,
                "known_for_department": "Acting",
                "name": "Masakazu Kuwayama",
                "original_name": "Masakazu Kuwayama",
                "popularity": 5.049,
                "profile_path": "/zUehHQ3FE3RB0DE7hiI8pJ1t6Af.jpg",
                "cast_id": 41,
                "character": "(segment \"Hoichi the Earless\") (uncredited)",
                "credit_id": "52fe444f9251416c9100c3a1",
                "order": 32
            },
            {
                "adult": false,
                "gender": 2,
                "id": 552653,
                "known_for_department": "Acting",
                "name": "Mutsuhiko Tsurumaru",
                "original_name": "Mutsuhiko Tsurumaru",
                "popularity": 0.6,
                "profile_path": null,
                "cast_id": 42,
                "character": "(segment \"Hoichi the Earless\") (uncredited)",
                "credit_id": "52fe444f9251416c9100c3a5",
                "order": 33
            },
            {
                "adult": false,
                "gender": 2,
                "id": 552167,
                "known_for_department": "Acting",
                "name": "Akira Tani",
                "original_name": "Akira Tani",
                "popularity": 2.343,
                "profile_path": "/pjSOz9Las7EEL2ugu9JUbZbv2Ks.jpg",
                "cast_id": 43,
                "character": "Huntsman #2 (segment \"Hoichi the Earless\") (uncredited)",
                "credit_id": "52fe444f9251416c9100c3a9",
                "order": 34
            },
            {
                "adult": false,
                "gender": 2,
                "id": 552654,
                "known_for_department": "Acting",
                "name": "Yousuke Kondou",
                "original_name": "Yousuke Kondou",
                "popularity": 1.986,
                "profile_path": "/afzm98rtX7WC4twn6AzdEHzlex5.jpg",
                "cast_id": 44,
                "character": "Benkei (segment \"Hoichi the Earless\") (uncredited)",
                "credit_id": "52fe444f9251416c9100c3ad",
                "order": 35
            },
            {
                "adult": false,
                "gender": 0,
                "id": 225539,
                "known_for_department": "Directing",
                "name": "Kiyoshi Yamamoto",
                "original_name": "Kiyoshi Yamamoto",
                "popularity": 1.96,
                "profile_path": null,
                "cast_id": 45,
                "character": "(segment \"Hoichi the Earless\") (uncredited)",
                "credit_id": "52fe444f9251416c9100c3b1",
                "order": 36
            },
            {
                "adult": false,
                "gender": 2,
                "id": 552655,
                "known_for_department": "Acting",
                "name": "Kinji Omino",
                "original_name": "Kinji Omino",
                "popularity": 1.008,
                "profile_path": null,
                "cast_id": 46,
                "character": "(segment \"Hoichi the Earless\") (uncredited)",
                "credit_id": "52fe444f9251416c9100c3b5",
                "order": 37
            },
            {
                "adult": false,
                "gender": 2,
                "id": 552656,
                "known_for_department": "Acting",
                "name": "Atsuo Nakamura",
                "original_name": "Atsuo Nakamura",
                "popularity": 5.002,
                "profile_path": "/mc5ObFxHMBHD0ThQJcu9OvvZ5DS.jpg",
                "cast_id": 47,
                "character": "(segment \"Hoichi the Earless\") (uncredited)",
                "credit_id": "52fe444f9251416c9100c3b9",
                "order": 38
            },
            {
                "adult": false,
                "gender": 0,
                "id": 96806,
                "known_for_department": "Acting",
                "name": "Ginz\u00f4 Sekiguchi",
                "original_name": "Ginz\u00f4 Sekiguchi",
                "popularity": 0.625,
                "profile_path": null,
                "cast_id": 48,
                "character": "(segment \"Hoichi the Earless\") (uncredited)",
                "credit_id": "52fe444f9251416c9100c3bd",
                "order": 39
            },
            {
                "adult": false,
                "gender": 2,
                "id": 552657,
                "known_for_department": "Acting",
                "name": "Akio Miyabe",
                "original_name": "Akio Miyabe",
                "popularity": 1.4,
                "profile_path": null,
                "cast_id": 49,
                "character": "(segment \"Hoichi the Earless\") (uncredited)",
                "credit_id": "52fe444f9251416c9100c3c1",
                "order": 40
            },
            {
                "adult": false,
                "gender": 2,
                "id": 552658,
                "known_for_department": "Acting",
                "name": "Gen'ya Nagai",
                "original_name": "Gen'ya Nagai",
                "popularity": 0.6,
                "profile_path": null,
                "cast_id": 50,
                "character": "(segment \"Hoichi the Earless\") (uncredited)",
                "credit_id": "52fe444f9251416c9100c3c5",
                "order": 41
            },
            {
                "adult": false,
                "gender": 0,
                "id": 552659,
                "known_for_department": "Acting",
                "name": "Toru Uchida",
                "original_name": "Toru Uchida",
                "popularity": 0.6,
                "profile_path": null,
                "cast_id": 51,
                "character": "(segment \"Hoichi the Earless\") (uncredited)",
                "credit_id": "52fe444f9251416c9100c3c9",
                "order": 42
            },
            {
                "adult": false,
                "gender": 0,
                "id": 552660,
                "known_for_department": "Acting",
                "name": "Hikaru Jinno",
                "original_name": "Hikaru Jinno",
                "popularity": 0.6,
                "profile_path": null,
                "cast_id": 52,
                "character": "(segment \"Hoichi the Earless\") (uncredited)",
                "credit_id": "52fe444f9251416c9100c3cd",
                "order": 43
            },
            {
                "adult": false,
                "gender": 0,
                "id": 552661,
                "known_for_department": "Acting",
                "name": "Toshio Fukuhara",
                "original_name": "Toshio Fukuhara",
                "popularity": 0.6,
                "profile_path": null,
                "cast_id": 53,
                "character": "(segment \"Hoichi the Earless\") (uncredited)",
                "credit_id": "52fe444f9251416c9100c3d1",
                "order": 44
            },
            {
                "adult": false,
                "gender": 0,
                "id": 552662,
                "known_for_department": "Acting",
                "name": "Kir\u00f4 Abe",
                "original_name": "Kir\u00f4 Abe",
                "popularity": 0.6,
                "profile_path": null,
                "cast_id": 54,
                "character": "(segment \"Hoichi the Earless\") (uncredited)",
                "credit_id": "52fe444f9251416c9100c3d5",
                "order": 45
            },
            {
                "adult": false,
                "gender": 0,
                "id": 552663,
                "known_for_department": "Acting",
                "name": "Toshiro Yagi",
                "original_name": "Toshiro Yagi",
                "popularity": 0.84,
                "profile_path": null,
                "cast_id": 55,
                "character": "(segment \"Hoichi the Earless\") (uncredited)",
                "credit_id": "52fe444f9251416c9100c3d9",
                "order": 46
            },
            {
                "adult": false,
                "gender": 1,
                "id": 552664,
                "known_for_department": "Acting",
                "name": "Yuriko Abe",
                "original_name": "Yuriko Abe",
                "popularity": 0.728,
                "profile_path": null,
                "cast_id": 56,
                "character": "(segment \"Hoichi the Earless\") (uncredited)",
                "credit_id": "52fe444f9251416c9100c3dd",
                "order": 47
            },
            {
                "adult": false,
                "gender": 0,
                "id": 552665,
                "known_for_department": "Acting",
                "name": "Yuri Sat\u00f4",
                "original_name": "Yuri Sat\u00f4",
                "popularity": 0.6,
                "profile_path": null,
                "cast_id": 57,
                "character": "(segment \"Hoichi the Earless\") (uncredited)",
                "credit_id": "52fe444f9251416c9100c3e1",
                "order": 48
            },
            {
                "adult": false,
                "gender": 2,
                "id": 136882,
                "known_for_department": "Acting",
                "name": "Ky\u014dichi Sat\u014d",
                "original_name": "Ky\u014dichi Sat\u014d",
                "popularity": 1.861,
                "profile_path": "/3PrzHdnpc50bU9DEb1EUhlgOlEo.jpg",
                "cast_id": 58,
                "character": "(segment \"Hoichi the Earless\") (uncredited)",
                "credit_id": "52fe444f9251416c9100c3e5",
                "order": 49
            },
            {
                "adult": false,
                "gender": 0,
                "id": 552666,
                "known_for_department": "Acting",
                "name": "Nobuo Aikawa",
                "original_name": "Nobuo Aikawa",
                "popularity": 0.6,
                "profile_path": null,
                "cast_id": 59,
                "character": "(segment \"Hoichi the Earless\") (uncredited)",
                "credit_id": "52fe444f9251416c9100c3e9",
                "order": 50
            },
            {
                "adult": false,
                "gender": 2,
                "id": 552667,
                "known_for_department": "Acting",
                "name": "Taiji Kodama",
                "original_name": "Taiji Kodama",
                "popularity": 0.84,
                "profile_path": null,
                "cast_id": 60,
                "character": "(segment \"Hoichi the Earless\") (uncredited)",
                "credit_id": "52fe444f9251416c9100c3ed",
                "order": 51
            },
            {
                "adult": false,
                "gender": 0,
                "id": 552668,
                "known_for_department": "Acting",
                "name": "Nobuaki Maeda",
                "original_name": "Nobuaki Maeda",
                "popularity": 0.6,
                "profile_path": null,
                "cast_id": 61,
                "character": "(segment \"Hoichi the Earless\") (uncredited)",
                "credit_id": "52fe444f9251416c9100c3f1",
                "order": 52
            },
            {
                "adult": false,
                "gender": 0,
                "id": 552669,
                "known_for_department": "Acting",
                "name": "Teruhiko Shibata",
                "original_name": "Teruhiko Shibata",
                "popularity": 1.176,
                "profile_path": null,
                "cast_id": 62,
                "character": "(segment \"Hoichi the Earless\") (uncredited)",
                "credit_id": "52fe444f9251416c9100c3f5",
                "order": 53
            },
            {
                "adult": false,
                "gender": 0,
                "id": 552670,
                "known_for_department": "Acting",
                "name": "Haruo Kaji",
                "original_name": "Haruo Kaji",
                "popularity": 0.6,
                "profile_path": null,
                "cast_id": 63,
                "character": "(segment \"Hoichi the Earless\") (uncredited)",
                "credit_id": "52fe444f9251416c9100c3f9",
                "order": 54
            },
            {
                "adult": false,
                "gender": 0,
                "id": 552671,
                "known_for_department": "Acting",
                "name": "Michio Gina",
                "original_name": "Michio Gina",
                "popularity": 0.6,
                "profile_path": null,
                "cast_id": 64,
                "character": "(segment \"Hoichi the Earless\") (uncredited)",
                "credit_id": "52fe444f9251416c9100c3fd",
                "order": 55
            },
            {
                "adult": false,
                "gender": 0,
                "id": 552672,
                "known_for_department": "Acting",
                "name": "Seiji Tabe",
                "original_name": "Seiji Tabe",
                "popularity": 0.6,
                "profile_path": null,
                "cast_id": 65,
                "character": "(segment \"Hoichi the Earless\") (uncredited)",
                "credit_id": "52fe444f9251416c9100c401",
                "order": 56
            },
            {
                "adult": false,
                "gender": 0,
                "id": 552673,
                "known_for_department": "Acting",
                "name": "Mitsuko Narita",
                "original_name": "Mitsuko Narita",
                "popularity": 0.6,
                "profile_path": null,
                "cast_id": 66,
                "character": "(segment \"Hoichi the Earless\") (uncredited)",
                "credit_id": "52fe444f9251416c9100c405",
                "order": 57
            },
            {
                "adult": false,
                "gender": 0,
                "id": 552674,
                "known_for_department": "Acting",
                "name": "Noriko Mikura",
                "original_name": "Noriko Mikura",
                "popularity": 0.6,
                "profile_path": null,
                "cast_id": 67,
                "character": "(segment \"Hoichi the Earless\") (uncredited)",
                "credit_id": "52fe444f9251416c9100c409",
                "order": 58
            },
            {
                "adult": false,
                "gender": 1,
                "id": 552675,
                "known_for_department": "Acting",
                "name": "Aiko Nagayama",
                "original_name": "Aiko Nagayama",
                "popularity": 1.553,
                "profile_path": "/ezE2uDofjzgSzpRWp1tJtwBBvGH.jpg",
                "cast_id": 68,
                "character": "(segment \"Hoichi the Earless\") (uncredited)",
                "credit_id": "52fe444f9251416c9100c40d",
                "order": 59
            },
            {
                "adult": false,
                "gender": 0,
                "id": 552676,
                "known_for_department": "Acting",
                "name": "Michiko Nakahata",
                "original_name": "Michiko Nakahata",
                "popularity": 0.6,
                "profile_path": null,
                "cast_id": 69,
                "character": "(segment \"Hoichi the Earless\") (uncredited)",
                "credit_id": "52fe444f9251416c9100c411",
                "order": 60
            },
            {
                "adult": false,
                "gender": 2,
                "id": 118984,
                "known_for_department": "Acting",
                "name": "Kan'emon Nakamura",
                "original_name": "Kan'emon Nakamura",
                "popularity": 3.798,
                "profile_path": "/9JEKx46uhnPBWuELipdD6t0TlST.jpg",
                "cast_id": 70,
                "character": "Kannai (segment \"In a Cup of Tea\")",
                "credit_id": "52fe444f9251416c9100c415",
                "order": 61
            },
            {
                "adult": false,
                "gender": 2,
                "id": 131923,
                "known_for_department": "Acting",
                "name": "Osamu Takizawa",
                "original_name": "Osamu Takizawa",
                "popularity": 4.056,
                "profile_path": "/zFKK5v1WhdkxH7RWL07pNvaeDRB.jpg",
                "cast_id": 71,
                "character": "Author / Narrator (segment \"In a Cup of Tea\")",
                "credit_id": "52fe444f9251416c9100c419",
                "order": 62
            },
            {
                "adult": false,
                "gender": 1,
                "id": 131013,
                "known_for_department": "Acting",
                "name": "Haruko Sugimura",
                "original_name": "Haruko Sugimura",
                "popularity": 3.003,
                "profile_path": "/g4ro32UO0Aob9QtLAVAXI9oOKZT.jpg",
                "cast_id": 72,
                "character": "Madame (segment \"In a Cup of Tea\")",
                "credit_id": "52fe444f9251416c9100c41d",
                "order": 63
            },
            {
                "adult": false,
                "gender": 2,
                "id": 140106,
                "known_for_department": "Acting",
                "name": "Noboru Nakaya",
                "original_name": "Noboru Nakaya",
                "popularity": 3.653,
                "profile_path": "/wZluvwUD2iCUukV5Ph6CUDHpALu.jpg",
                "cast_id": 74,
                "character": "Shikibu Heinai (segment \"In a Cup of Tea\")",
                "credit_id": "52fe444f9251416c9100c425",
                "order": 64
            },
            {
                "adult": false,
                "gender": 2,
                "id": 20829,
                "known_for_department": "Acting",
                "name": "Seiji Miyaguchi",
                "original_name": "Seiji Miyaguchi",
                "popularity": 6.025,
                "profile_path": "/97XiJh1TSdu4hmJUp4Am5afgBZx.jpg",
                "cast_id": 75,
                "character": "Old Man (segment \"In a Cup of Tea\")",
                "credit_id": "52fe444f9251416c9100c429",
                "order": 65
            },
            {
                "adult": false,
                "gender": 2,
                "id": 33730,
                "known_for_department": "Acting",
                "name": "Kei Sat\u014d",
                "original_name": "Kei Sat\u014d",
                "popularity": 7.194,
                "profile_path": "/xVTrBHHVWrGBQ3ubhTa8z8upb1R.jpg",
                "cast_id": 76,
                "character": "Ghost Samurai (segment \"In a Cup of Tea\")",
                "credit_id": "52fe444f9251416c9100c42d",
                "order": 66
            },
            {
                "adult": false,
                "gender": 2,
                "id": 34690,
                "known_for_department": "Acting",
                "name": "Shigeru K\u014dyama",
                "original_name": "Shigeru K\u014dyama",
                "popularity": 2.932,
                "profile_path": "/znvahZRfGrpUaWb2N8NZiugZFVa.jpg",
                "cast_id": 77,
                "character": "(segment \"In a Cup of Tea\") (uncredited)",
                "credit_id": "52fe44509251416c9100c431",
                "order": 67
            },
            {
                "adult": false,
                "gender": 2,
                "id": 30470,
                "known_for_department": "Acting",
                "name": "Jun Tazaki",
                "original_name": "Jun Tazaki",
                "popularity": 3.735,
                "profile_path": "/xCaRyiMo8sleDYjLKGl8xUXsIHQ.jpg",
                "cast_id": 78,
                "character": "Kannai's Colleague #1 (segment \"In a Cup of Tea\") (uncredited)",
                "credit_id": "52fe44509251416c9100c435",
                "order": 68
            },
            {
                "adult": false,
                "gender": 2,
                "id": 226744,
                "known_for_department": "Acting",
                "name": "Junkichi Orimoto",
                "original_name": "Junkichi Orimoto",
                "popularity": 3.241,
                "profile_path": "/tW3lTUVeVJKVh56SKV31Z6MwRWF.jpg",
                "cast_id": 79,
                "character": "(segment \"In a Cup of Tea\") (uncredited)",
                "credit_id": "52fe44509251416c9100c439",
                "order": 69
            },
            {
                "adult": false,
                "gender": 2,
                "id": 119185,
                "known_for_department": "Acting",
                "name": "Akiji Kobayashi",
                "original_name": "Akiji Kobayashi",
                "popularity": 3.651,
                "profile_path": "/yW9v9sIDGmox7RfF7wFqqrlIKDU.jpg",
                "cast_id": 80,
                "character": "(segment \"In a Cup of Tea\") (uncredited)",
                "credit_id": "52fe44509251416c9100c43d",
                "order": 70
            },
            {
                "adult": false,
                "gender": 2,
                "id": 226742,
                "known_for_department": "Acting",
                "name": "Yoshir\u014d Aoki",
                "original_name": "Yoshir\u014d Aoki",
                "popularity": 2.787,
                "profile_path": "/50xy62RmFeLC7NCfmNCJuA5mpfT.jpg",
                "cast_id": 81,
                "character": "(segment \"In a Cup of Tea\") (uncredited)",
                "credit_id": "52fe44509251416c9100c441",
                "order": 71
            },
            {
                "adult": false,
                "gender": 2,
                "id": 82478,
                "known_for_department": "Acting",
                "name": "Isao Tamagawa",
                "original_name": "Isao Tamagawa",
                "popularity": 1.547,
                "profile_path": "/ApIkj4MwUbFNqvmlvUHCLtlua0H.jpg",
                "cast_id": 82,
                "character": "(segment \"In a Cup of Tea\") (uncredited)",
                "credit_id": "52fe44509251416c9100c445",
                "order": 72
            },
            {
                "adult": false,
                "gender": 2,
                "id": 227622,
                "known_for_department": "Acting",
                "name": "Hideyo Amamoto",
                "original_name": "Hideyo Amamoto",
                "popularity": 3.461,
                "profile_path": "/5hPGmYj0FEaFC8Dij7xpIcG6waT.jpg",
                "cast_id": 83,
                "character": "(segment \"In a Cup of Tea\") (uncredited)",
                "credit_id": "52fe44509251416c9100c449",
                "order": 73
            },
            {
                "adult": false,
                "gender": 2,
                "id": 1378968,
                "known_for_department": "Acting",
                "name": "Ganjir\u014d Nakamura II",
                "original_name": "Ganjir\u014d Nakamura II",
                "popularity": 2.233,
                "profile_path": "/ydnV6jwLnDpSpgZWQtgU4us5TRH.jpg",
                "cast_id": 113,
                "character": "Publisher (segment \"In a Cup of Tea\")",
                "credit_id": "61421e5d006b010063f01c86",
                "order": 74
            }
        ],
        "crew": [
            {
                "adult": false,
                "gender": 2,
                "id": 51808,
                "known_for_department": "Sound",
                "name": "Toru Takemitsu",
                "original_name": "Toru Takemitsu",
                "popularity": 1.271,
                "profile_path": "/l48fEVb1HGMilTCkxSzYuZsSPdk.jpg",
                "credit_id": "52fe444f9251416c9100c30b",
                "department": "Sound",
                "job": "Original Music Composer"
            },
            {
                "adult": false,
                "gender": 2,
                "id": 51808,
                "known_for_department": "Sound",
                "name": "Toru Takemitsu",
                "original_name": "Toru Takemitsu",
                "popularity": 1.271,
                "profile_path": "/l48fEVb1HGMilTCkxSzYuZsSPdk.jpg",
                "credit_id": "5e08542726dac1001475f7ff",
                "department": "Sound",
                "job": "Sound Designer"
            },
            {
                "adult": false,
                "gender": 2,
                "id": 76978,
                "known_for_department": "Directing",
                "name": "Masaki Kobayashi",
                "original_name": "Masaki Kobayashi",
                "popularity": 7.368,
                "profile_path": "/5epZ39mf1Ii7xOjqYx2YYq39y5X.jpg",
                "credit_id": "52fe444f9251416c9100c2f3",
                "department": "Directing",
                "job": "Director"
            },
            {
                "adult": false,
                "gender": 1,
                "id": 125691,
                "known_for_department": "Writing",
                "name": "Yoko Mizuki",
                "original_name": "Yoko Mizuki",
                "popularity": 2.892,
                "profile_path": "/6EVkY3Qqtm8aqAntQb3g168gKAz.jpg",
                "credit_id": "52fe444f9251416c9100c2f9",
                "department": "Writing",
                "job": "Screenplay"
            },
            {
                "adult": false,
                "gender": 2,
                "id": 550944,
                "known_for_department": "Art",
                "name": "Kiyoshi Awazu",
                "original_name": "Kiyoshi Awazu",
                "popularity": 0.6,
                "profile_path": "/nh2TM8W7kUawG7d3hC4Co1poPOw.jpg",
                "credit_id": "5e08579326dac10017750246",
                "department": "Art",
                "job": "Title Designer"
            },
            {
                "adult": false,
                "gender": 2,
                "id": 550945,
                "known_for_department": "Sound",
                "name": "Hideo Nishizaki",
                "original_name": "Hideo Nishizaki",
                "popularity": 1.084,
                "profile_path": null,
                "credit_id": "5e08539a4c1d9a0019e44011",
                "department": "Sound",
                "job": "Sound"
            },
            {
                "adult": false,
                "gender": 0,
                "id": 552163,
                "known_for_department": "Costume & Make-Up",
                "name": "Masahiro Kat\u014d",
                "original_name": "Masahiro Kat\u014d",
                "popularity": 1.235,
                "profile_path": null,
                "credit_id": "5e08524d127778001412cf6f",
                "department": "Costume & Make-Up",
                "job": "Costume Design"
            },
            {
                "adult": false,
                "gender": 0,
                "id": 552307,
                "known_for_department": "Production",
                "name": "Shigeru Wakatsuki",
                "original_name": "Shigeru Wakatsuki",
                "popularity": 0.84,
                "profile_path": null,
                "credit_id": "52fe444f9251416c9100c305",
                "department": "Production",
                "job": "Producer"
            },
            {
                "adult": false,
                "gender": 0,
                "id": 552308,
                "known_for_department": "Camera",
                "name": "Yoshio Miyajima",
                "original_name": "Yoshio Miyajima",
                "popularity": 1.947,
                "profile_path": null,
                "credit_id": "52fe444f9251416c9100c311",
                "department": "Crew",
                "job": "Cinematography"
            },
            {
                "adult": false,
                "gender": 0,
                "id": 552637,
                "known_for_department": "Writing",
                "name": "Lafcadio Hearn",
                "original_name": "Lafcadio Hearn",
                "popularity": 1.708,
                "profile_path": null,
                "credit_id": "52fe444f9251416c9100c2ff",
                "department": "Writing",
                "job": "Novel"
            },
            {
                "adult": false,
                "gender": 0,
                "id": 552638,
                "known_for_department": "Editing",
                "name": "Hisashi Sagara",
                "original_name": "Hisashi Sagara",
                "popularity": 0.98,
                "profile_path": null,
                "credit_id": "52fe444f9251416c9100c317",
                "department": "Editing",
                "job": "Editor"
            },
            {
                "adult": false,
                "gender": 2,
                "id": 552639,
                "known_for_department": "Art",
                "name": "Shigemasa Toda",
                "original_name": "Shigemasa Toda",
                "popularity": 0.972,
                "profile_path": null,
                "credit_id": "52fe444f9251416c9100c31d",
                "department": "Art",
                "job": "Art Direction"
            },
            {
                "adult": false,
                "gender": 2,
                "id": 1093432,
                "known_for_department": "Camera",
                "name": "Yasuhiro Yoshioka",
                "original_name": "Yasuhiro Yoshioka",
                "popularity": 0.732,
                "profile_path": null,
                "credit_id": "5e0854df5ff34e0011b7ddac",
                "department": "Camera",
                "job": "Still Photographer"
            },
            {
                "adult": false,
                "gender": 0,
                "id": 1183036,
                "known_for_department": "Costume & Make-Up",
                "name": "Yoshio Ueno",
                "original_name": "Yoshio Ueno",
                "popularity": 0.6,
                "profile_path": null,
                "credit_id": "5e0855bcd285af001191acb3",
                "department": "Costume & Make-Up",
                "job": "Costume Consultant"
            },
            {
                "adult": false,
                "gender": 0,
                "id": 1472695,
                "known_for_department": "Production",
                "name": "Kazuo Kuwahara",
                "original_name": "Kazuo Kuwahara",
                "popularity": 0.6,
                "profile_path": null,
                "credit_id": "5e0852b7127778001412cfd8",
                "department": "Production",
                "job": "Production Supervisor"
            },
            {
                "adult": false,
                "gender": 0,
                "id": 1547560,
                "known_for_department": "Directing",
                "name": "G\u00f4 Yoshida",
                "original_name": "G\u00f4 Yoshida",
                "popularity": 0.6,
                "profile_path": null,
                "credit_id": "5e0853125aadc400152c3f34",
                "department": "Directing",
                "job": "First Assistant Director"
            },
            {
                "adult": false,
                "gender": 0,
                "id": 1565273,
                "known_for_department": "Art",
                "name": "Dai Arakawa",
                "original_name": "Dai Arakawa",
                "popularity": 1.041,
                "profile_path": null,
                "credit_id": "5e085227eda4b700122e6021",
                "department": "Art",
                "job": "Set Decoration"
            },
            {
                "adult": false,
                "gender": 0,
                "id": 1602592,
                "known_for_department": "Sound",
                "name": "Shigenosuke Okuyama",
                "original_name": "Shigenosuke Okuyama",
                "popularity": 0.6,
                "profile_path": null,
                "credit_id": "5e0853b8a1c59d0016a9431b",
                "department": "Sound",
                "job": "Sound Designer"
            },
            {
                "adult": false,
                "gender": 0,
                "id": 1608752,
                "known_for_department": "Editing",
                "name": "Eiko Yoshida",
                "original_name": "Eiko Yoshida",
                "popularity": 0.6,
                "profile_path": null,
                "credit_id": "5e0857725ff34e0017b81bd6",
                "department": "Directing",
                "job": "Continuity"
            },
            {
                "adult": false,
                "gender": 0,
                "id": 1711777,
                "known_for_department": "Costume & Make-Up",
                "name": "Ayako Sakurai",
                "original_name": "Ayako Sakurai",
                "popularity": 0.6,
                "profile_path": null,
                "credit_id": "5e085270d236e60010a1a3ce",
                "department": "Costume & Make-Up",
                "job": "Hairstylist"
            },
            {
                "adult": false,
                "gender": 0,
                "id": 1722920,
                "known_for_department": "Production",
                "name": "Michiyoshi Takashima",
                "original_name": "Michiyoshi Takashima",
                "popularity": 0.98,
                "profile_path": null,
                "credit_id": "5e0852d84c1d9a0015e406f6",
                "department": "Production",
                "job": "Executive In Charge Of Production"
            },
            {
                "adult": false,
                "gender": 0,
                "id": 1981050,
                "known_for_department": "Costume & Make-Up",
                "name": "Shigeru Takagi",
                "original_name": "Shigeru Takagi",
                "popularity": 0.6,
                "profile_path": null,
                "credit_id": "5e085298a1c59d001ba8d854",
                "department": "Costume & Make-Up",
                "job": "Makeup Artist"
            },
            {
                "adult": false,
                "gender": 0,
                "id": 2113155,
                "known_for_department": "Lighting",
                "name": "Akira Aomatsu",
                "original_name": "Akira Aomatsu",
                "popularity": 0.6,
                "profile_path": null,
                "credit_id": "5e0854885aadc400122bd0d3",
                "department": "Lighting",
                "job": "Gaffer"
            },
            {
                "adult": false,
                "gender": 0,
                "id": 2493112,
                "known_for_department": "Production",
                "name": "Y\u00f4ichi Ukita",
                "original_name": "Y\u00f4ichi Ukita",
                "popularity": 0.6,
                "profile_path": null,
                "credit_id": "5e0852f39bcd0f00171385d9",
                "department": "Production",
                "job": "Production Supervisor"
            },
            {
                "adult": false,
                "gender": 0,
                "id": 2493113,
                "known_for_department": "Art",
                "name": "Kiyoharu Matsuno",
                "original_name": "Kiyoharu Matsuno",
                "popularity": 0.6,
                "profile_path": null,
                "credit_id": "5e08532e127778001412d3a4",
                "department": "Art",
                "job": "Set Designer"
            },
            {
                "adult": false,
                "gender": 0,
                "id": 2493115,
                "known_for_department": "Art",
                "name": "Naotake Satsumoto",
                "original_name": "Naotake Satsumoto",
                "popularity": 0.6,
                "profile_path": null,
                "credit_id": "5e08535fd285af0011919945",
                "department": "Art",
                "job": "Assistant Art Director"
            },
            {
                "adult": false,
                "gender": 2,
                "id": 2493116,
                "known_for_department": "Sound",
                "name": "Kuniharu Akiyama",
                "original_name": "Kuniharu Akiyama",
                "popularity": 0.6,
                "profile_path": null,
                "credit_id": "5e08537cd285af001391679d",
                "department": "Sound",
                "job": "Sound Designer"
            },
            {
                "adult": false,
                "gender": 0,
                "id": 2493117,
                "known_for_department": "Sound",
                "name": "Masaharu Shioda",
                "original_name": "Masaharu Shioda",
                "popularity": 0.6,
                "profile_path": null,
                "credit_id": "5e0853daeda4b700172e5bfd",
                "department": "Sound",
                "job": "Sound Recordist"
            },
            {
                "adult": false,
                "gender": 2,
                "id": 2493118,
                "known_for_department": "Sound",
                "name": "Akira Suzuki",
                "original_name": "Akira Suzuki",
                "popularity": 0.98,
                "profile_path": null,
                "credit_id": "5e085408eda4b700122e6d59",
                "department": "Sound",
                "job": "Sound Designer"
            },
            {
                "adult": false,
                "gender": 0,
                "id": 2493121,
                "known_for_department": "Sound",
                "name": "Kazutoshi Yagihashi",
                "original_name": "Kazutoshi Yagihashi",
                "popularity": 0.694,
                "profile_path": null,
                "credit_id": "5e085441d236e60010a1b043",
                "department": "Sound",
                "job": "Sound Recordist"
            },
            {
                "adult": false,
                "gender": 0,
                "id": 2493122,
                "known_for_department": "Crew",
                "name": "Tatsuo Hotta",
                "original_name": "Tatsuo Hotta",
                "popularity": 0.6,
                "profile_path": null,
                "credit_id": "5e08545fd285af0013916cfd",
                "department": "Crew",
                "job": "Martial Arts Choreographer"
            },
            {
                "adult": false,
                "gender": 0,
                "id": 2493123,
                "known_for_department": "Camera",
                "name": "Toshiyuki Isobe",
                "original_name": "Toshiyuki Isobe",
                "popularity": 0.6,
                "profile_path": null,
                "credit_id": "5e0854a45aadc400152c4b81",
                "department": "Camera",
                "job": "Assistant Camera"
            },
            {
                "adult": false,
                "gender": 0,
                "id": 2493124,
                "known_for_department": "Camera",
                "name": "Sh\u00f4jir\u00f4 Kamohara",
                "original_name": "Sh\u00f4jir\u00f4 Kamohara",
                "popularity": 0.6,
                "profile_path": null,
                "credit_id": "5e0854be127778001912e2fc",
                "department": "Camera",
                "job": "Second Assistant Camera"
            },
            {
                "adult": false,
                "gender": 0,
                "id": 2493136,
                "known_for_department": "Editing",
                "name": "Shigeyuki Sekine",
                "original_name": "Shigeyuki Sekine",
                "popularity": 0.6,
                "profile_path": null,
                "credit_id": "5e0856cba1c59d0016a95719",
                "department": "Editing",
                "job": "Colorist"
            },
            {
                "adult": false,
                "gender": 0,
                "id": 2493143,
                "known_for_department": "Editing",
                "name": "Junichir\u00f4 \u00d4saka",
                "original_name": "Junichir\u00f4 \u00d4saka",
                "popularity": 0.6,
                "profile_path": null,
                "credit_id": "5e08572b4c1d9a0013e40ba3",
                "department": "Editing",
                "job": "Assistant Editor"
            },
            {
                "adult": false,
                "gender": 0,
                "id": 2493144,
                "known_for_department": "Sound",
                "name": "Kinji Tsuruda",
                "original_name": "Kinji Tsuruda",
                "popularity": 0.6,
                "profile_path": null,
                "credit_id": "5e085743a1c59d001ba8edf5",
                "department": "Sound",
                "job": "Musician"
            },
            {
                "adult": false,
                "gender": 0,
                "id": 2493145,
                "known_for_department": "Production",
                "name": "Tadanosuke Sumida",
                "original_name": "Tadanosuke Sumida",
                "popularity": 0.6,
                "profile_path": null,
                "credit_id": "5e0857abd285af001191b5be",
                "department": "Production",
                "job": "Researcher"
            }
        ]
    },
    "videos": {
        "results": [
            {
                "iso_639_1": "en",
                "iso_3166_1": "US",
                "name": "KWAIDAN (Masters of Cinema) New & Exclusive Trailer",
                "key": "YadApPG8W7Q",
                "site": "YouTube",
                "size": 1080,
                "type": "Trailer",
                "official": true,
                "published_at": "2020-02-25T12:00:05.000Z",
                "id": "5ebd43de076ce8001f74d133"
            },
            {
                "iso_639_1": "en",
                "iso_3166_1": "US",
                "name": "Ernest Dickerson on KWAIDAN",
                "key": "etZY_Y6mWw8",
                "published_at": "2018-03-12T01:00:03.000Z",
                "site": "YouTube",
                "size": 720,
                "type": "Featurette",
                "official": false,
                "id": "5b26ebdf9251410d5c014d32"
            }
        ]
    },
    "images": {
        "backdrops": [
            {
                "aspect_ratio": 1.778,
                "height": 900,
                "iso_639_1": null,
                "file_path": "/y8G11KP4qNY2251ufNezKF92EAR.jpg",
                "vote_average": 5.312,
                "vote_count": 1,
                "width": 1600
            },
            {
                "aspect_ratio": 1.777,
                "height": 799,
                "iso_639_1": null,
                "file_path": "/hVGRef6zIOarZW6Zc9lqAx4E4bq.jpg",
                "vote_average": 5.172,
                "vote_count": 1,
                "width": 1420
            },
            {
                "aspect_ratio": 1.778,
                "height": 2160,
                "iso_639_1": "en",
                "file_path": "/dL6uZ1Mww1cROoo7qZVNAhjM654.jpg",
                "vote_average": 0.0,
                "vote_count": 0,
                "width": 3840
            }
        ],
        "logos": [],
        "posters": [
            {
                "aspect_ratio": 0.666,
                "height": 1597,
                "iso_639_1": "ja",
                "file_path": "/lxOxZVhGkmnz7jFJDS8EfkhxmmN.jpg",
                "vote_average": 5.312,
                "vote_count": 1,
                "width": 1064
            },
            {
                "aspect_ratio": 0.703,
                "height": 2844,
                "iso_639_1": "ja",
                "file_path": "/3QzqveuUByQ8SM3gCCwY1t4rOSO.jpg",
                "vote_average": 5.312,
                "vote_count": 1,
                "width": 2000
            },
            {
                "aspect_ratio": 0.67,
                "height": 1100,
                "iso_639_1": "ja",
                "file_path": "/yv338DHY83dSNQNPEQjH4q6amAt.jpg",
                "vote_average": 5.312,
                "vote_count": 1,
                "width": 737
            },
            {
                "aspect_ratio": 0.701,
                "height": 1426,
                "iso_639_1": "en",
                "file_path": "/cfcIjq4V8GxtMN6GU3WnufTM9cD.jpg",
                "vote_average": 5.246,
                "vote_count": 2,
                "width": 1000
            },
            {
                "aspect_ratio": 0.669,
                "height": 1400,
                "iso_639_1": "en",
                "file_path": "/84bEhOgVMMZodVXg2BirTe0yRY3.jpg",
                "vote_average": 5.246,
                "vote_count": 2,
                "width": 937
            },
            {
                "aspect_ratio": 0.667,
                "height": 1800,
                "iso_639_1": "en",
                "file_path": "/tUAIqDstBOqpvlNIOiNzfyNGM6O.jpg",
                "vote_average": 5.246,
                "vote_count": 2,
                "width": 1200
            },
            {
                "aspect_ratio": 0.667,
                "height": 1200,
                "iso_639_1": "en",
                "file_path": "/vmYhFcA2YC15hoL44hQziba75Ij.jpg",
                "vote_average": 5.206,
                "vote_count": 9,
                "width": 800
            },
            {
                "aspect_ratio": 0.667,
                "height": 2100,
                "iso_639_1": "en",
                "file_path": "/t9UMfViYl47SdZZatKQ1JKjjCgs.jpg",
                "vote_average": 5.198,
                "vote_count": 7,
                "width": 1400
            },
            {
                "aspect_ratio": 0.668,
                "height": 2900,
                "iso_639_1": "en",
                "file_path": "/9GXpAOtap91iMGAcgSi1SM9fcN.jpg",
                "vote_average": 5.118,
                "vote_count": 4,
                "width": 1936
            },
            {
                "aspect_ratio": 0.667,
                "height": 2100,
                "iso_639_1": "en",
                "file_path": "/hOwahpfNj14SbRe09xiWsuOH8xs.jpg",
                "vote_average": 5.106,
                "vote_count": 2,
                "width": 1400
            },
            {
                "aspect_ratio": 0.667,
                "height": 1200,
                "iso_639_1": "en",
                "file_path": "/ccntRqevIrrOKiYGCJspJ9BkPNC.jpg",
                "vote_average": 5.044,
                "vote_count": 3,
                "width": 800
            },
            {
                "aspect_ratio": 0.667,
                "height": 1533,
                "iso_639_1": "ja",
                "file_path": "/4rJcStpcgyOZwKA0uCOLKbTFIow.jpg",
                "vote_average": 0.0,
                "vote_count": 0,
                "width": 1022
            },
            {
                "aspect_ratio": 0.667,
                "height": 2100,
                "iso_639_1": "ja",
                "file_path": "/dky1ba2RSnB52MsSbYnbFY9ueCu.jpg",
                "vote_average": 0.0,
                "vote_count": 0,
                "width": 1400
            },
            {
                "aspect_ratio": 0.667,
                "height": 1440,
                "iso_639_1": "en",
                "file_path": "/sFK2pWSePL86Vb8kxvyo4ka861S.jpg",
                "vote_average": 0.0,
                "vote_count": 0,
                "width": 960
            },
            {
                "aspect_ratio": 0.667,
                "height": 945,
                "iso_639_1": "es",
                "file_path": "/l22SG9evZiz3wp7E29dpl16XSO5.jpg",
                "vote_average": 0.0,
                "vote_count": 0,
                "width": 630
            },
            {
                "aspect_ratio": 0.667,
                "height": 1920,
                "iso_639_1": null,
                "file_path": "/p71ehOxRC3ijeXUoafPG4GXGpVk.jpg",
                "vote_average": 0.0,
                "vote_count": 0,
                "width": 1280
            },
            {
                "aspect_ratio": 0.667,
                "height": 1500,
                "iso_639_1": "en",
                "file_path": "/pNrOmmef7aGxgB9zwSH1JrqjXAr.jpg",
                "vote_average": 0.0,
                "vote_count": 0,
                "width": 1000
            },
            {
                "aspect_ratio": 0.681,
                "height": 2048,
                "iso_639_1": "is",
                "file_path": "/dkFpEGxPN9YY5E27HZhsZTlvwjh.jpg",
                "vote_average": 0.0,
                "vote_count": 0,
                "width": 1395
            },
            {
                "aspect_ratio": 0.666,
                "height": 1000,
                "iso_639_1": "it",
                "file_path": "/n0LgNPFNLOpHN89LP3YOkTWDG8s.jpg",
                "vote_average": 0.0,
                "vote_count": 0,
                "width": 666
            }
        ]
    },
    "keywords": {
        "keywords": [
            {
                "id": 1462,
                "name": "samurai"
            },
            {
                "id": 818,
                "name": "based on novel or book"
            },
            {
                "id": 3206,
                "name": "story teller"
            },
            {
                "id": 3373,
                "name": "snowstorm"
            },
            {
                "id": 4262,
                "name": "tea"
            },
            {
                "id": 6044,
                "name": "promise"
            },
            {
                "id": 10794,
                "name": "snow"
            },
            {
                "id": 12660,
                "name": "blind"
            },
            {
                "id": 13153,
                "name": "spirit"
            },
            {
                "id": 41411,
                "name": "vengeful ghost"
            },
            {
                "id": 156580,
                "name": "ghost story"
            },
            {
                "id": 162846,
                "name": "ghost"
            },
            {
                "id": 182677,
                "name": "sea battle"
            },
            {
                "id": 194938,
                "name": "japanese folklore"
            },
            {
                "id": 226475,
                "name": "naval battle"
            },
            {
                "id": 250593,
                "name": "horror anthology"
            },
            {
                "id": 287878,
                "name": "ghost in the woods"
            }
        ]
    },
    "title_english": "Kwaidan",
    "year": "1964",
    "rated": "Not Rated",
    "director_list": [
        "Masaki Kobayashi"
    ],
    "writer_list": [
        "Y\u00f4ko Mizuki",
        " Lafcadio Hearn"
    ],
    "main_cast": [
        "Rentar\u00f4 Mikuni",
        " Michiyo Aratama",
        " Misako Watanabe"
    ],
    "ratings": [
        {
            "Source": "Internet Movie Database",
            "Value": "7.9/10"
        },
        {
            "Source": "Rotten Tomatoes",
            "Value": "91%"
        }
    ],
    "imdb_rating": "7.9",
    "imdb_votes": "19,410",
    "wikipedia_url": "https://en.wikipedia.org/wiki/Kaidan",
    "wikipedia_summary": "Kaidan (\u602a\u8ac7, sometimes transliterated kwaidan) is a Japanese word consisting of two kanji: \u602a (kai) meaning \"strange, mysterious, rare, or bewitching apparition\" and \u8ac7 (dan) meaning \"talk\" or \"recited narrative\".",
    "wikipedia_plot": null,
    "wikipedia_plot_html": null,
    "wikipedia_critics": null,
    "wikipedia_full_html": "<link rel=\"mw-deduplicated-inline-style\" href=\"mw-data:TemplateStyles:r1033289096\">\n<p><i><b>Kaidan</b></i><span> (<span title=\"Japanese-language text\"><span lang=\"ja\">\u602a\u8ac7</span></span>, sometimes transliterated <i>kwaidan</i>)</span> is a Japanese word consisting of two kanji: \u602a (<i>kai</i>) meaning \"strange, mysterious, rare, or bewitching apparition\" and \u8ac7 (<i>dan</i>) meaning \"talk\" or \"recited narrative\".\n</p>\n\n<h2>Overall meaning and usage</h2>\n<p>In its broadest sense, <i>kaidan</i> refers to any ghost story or horror story, but it has an old-fashioned ring to it that carries the connotation of Edo period Japanese folktales. The term is no longer as widely used in Japanese as it once was: Japanese horror books and films such as <i>Ju-on</i> and <i>Ring</i> would more likely be labeled by the <i>katakana</i> <i>hor\u0101</i><span> (<span title=\"Japanese-language text\"><span lang=\"ja\">\u30db\u30e9\u30fc</span></span>, \"horror\")</span>. <i>Kaidan</i> is only used if the author/director wishes to specifically bring an old-fashioned air into the story.</p>\n\n<h3>Examples of <i>kaidan</i></h3>\n<ul><li><i>Banch\u014d Sarayashiki</i> (<i>The Story of Okiku</i>) by Okamoto Kido</li>\n<li><i>Yotsuya Kaidan</i> (<i>Ghost Story of T\u014dkaid\u014d Yotsuya</i>) by Tsuruya Nanboku IV (1755\u20131829)</li>\n<li><i>Botan D\u014dr\u014d</i> (<i>The Peony Lantern</i>) by Asai Ryoi</li>\n<li><i>Mimi-nashi H\u014dichi</i> (<i>H\u014dichi the Earless</i>)</li></ul>\n\n<h2><i>Hyakumonogatari Kaidankai</i> and <i>kaidanshu</i></h2>\n<p><i>Kaidan</i> entered the vernacular during the Edo period, when a parlour game called <i>Hyakumonogatari Kaidankai</i> became popular. This game led to a demand for ghost stories and folktales to be gathered from all parts of Japan and China.The popularity of the game, as well as the acquisition of a printing press, led to the creation of a literary genre called <i>kaidanshu</i>. <i>Kaidanshu</i> were originally based on older Buddhist stories of a didactic nature, although the moral lessons soon gave way to the demand for strange and gruesome stories.\n</p>\n\n<h3>Examples of <i>kaidanshu</i></h3>\n<ul><li><i>Tonoigusa</i>, called <i>Otogi Monogatari</i> (<i>Nursery Tales</i>) by Ogita Ansei (1660)</li>\n<li><i>Otogi Boko</i> (<i>Handpuppets</i>) by Asai Ryoi (1666)</li>\n<li><i>Ugetsu Monogatari</i> (<i>Tales of Moonlight and Rain</i>) by Ueda Akinari (1776)</li></ul>\n\n<h2>Background of the romanized translation</h2>\n<p>The word was popularised in English by Lafcadio Hearn in his book <i>Kwaidan: Stories and Studies of Strange Things</i>. The spelling <i><b>kwaidan</b></i> is a romanization based on an archaic spelling of the word in kana - Hearn used it since the stories in the book were equally archaic. The revised Hepburn romanization system is spelled <b>kaidan</b>.\n</p><p>When film director Masaki Kobayashi made his anthology film <i>Kwaidan</i> (1964) from Hearn's translated tales, the old spelling was used in the English title.\n</p>\n\n<h2>Plot elements</h2>\n<p>Originally based on didactic Buddhist tales, kaidan often involve elements of karma, and especially ghostly vengeance for misdeeds.  Japanese vengeful ghosts (<i>Onry\u014d</i>) are far more powerful after death than they were in life, and are often people who were particularly powerless in life, such as women and servants.\n</p><p>This vengeance is usually specifically targeted against the tormentor, but can sometimes be a general hatred toward all living humans.  This untargeted wrath can be seen in <i>Furisode</i>, a story in Hearn's book <i>In Ghostly Japan</i> about a cursed kimono that kills everyone who wears it.  This motif is repeated in the film <i>Ring</i> with a videotape that kills all who watch it, and the film franchise <i>Ju-on</i> with a house that kills all who enter it.\n</p><p>Kaidan also frequently involve water as a ghostly element.  In Japanese religion, water is a pathway to the underworld as can be seen in the festival of Obon.\n</p>\n\n<h2>See also</h2>\n<ul><li><i>Yose</i></li>\n<li>Glen Grant</li>\n<li>Japanese horror</li>\n<li>Japanese mythology</li>\n<li>Junji Ito</li>\n<li><i>Obake</i></li>\n<li>Shigeru Mizuki</li>\n<li><i>The Unbelievable</i></li>\n<li><i>Y\u014dkai</i></li>\n<li><i>Y\u016brei</i></li>\n<li>Aesop's Fables</li></ul>\n\n<h2>External links</h2>\n<ul><li>Ghoul Power - Onryou in the Movies Archived 2007-10-13 at the Wayback Machine <i>Japanzine</i> By Jon Wilks</li>\n<li>Tales of Ghostly Japan <i>Japanzine</i> By Zack Davisson</li>\n<li>Japanese Ghosts<i>Mangajin #40</i> by Tim Screech</li>\n<li>Hearn's <i>Kwaidan: Stories and Studies of Strange Things</i>.</li>\n<li>A site with several kaidan.</li>\n<li>Asian Folklore Studies: The Appeal of Kaidan Tales of the Strange.</li>\n<li>Information on <i>The Kaidan Suite,</i> a musical interpretation of kaidan by the Kitsune Ensemble.</li>\n<li>Hyakumonogatari.com A website of translated kaidan</li>\n<li>TheJapaneseHorror.com Website with several translated Kaidan</li></ul>"
}